xefab/__init__.py
xefab/collection.py
xefab/config.py
xefab/entrypoints.py
xefab/file_access.py
xefab/hosts/__init__.py
xefab/hosts/osg.py
xefab/hosts/uchicago/__init__.py
xefab/hosts/uchicago/dali.py
xefab/hosts/uchicago/midway.py
xefab/hosts/uchicago/midway3.py
xefab/main.py
xefab/pydantic_support.py
xefab/ssh_client.py
xefab/tasks/__init__.py
xefab/tasks/admin.py
xefab/tasks/batchq.py
xefab/tasks/condorq.py
xefab/tasks/github.py
xefab/tasks/install.py
xefab/tasks/jupyter.py
xefab/tasks/main.py
xefab/tasks/mc_chain.py
xefab/tasks/secrets.py
xefab/tasks/shell.py
xefab/tasks/squeue.py
xefab/tasks/transfer.py
xefab/tasks/utils.py
xefab/utils.py
xefab-0.1.13.dist-info/METADATA
xefab-0.1.13.dist-info/WHEEL
xefab-0.1.13.dist-info/entry_points.txt
xefab-0.1.13.dist-info/RECORD
