Metadata-Version: 2.1
Name: xefab
Version: 0.1.13
Summary: Top-level package for xefab.
Home-page: https://github.com/jmosbacher/xefab
Author: Yossi Mosbacher
Author-email: joe.mosbacher@gmail.com
Requires-Python: >=3.8
Classifier: Development Status :: 2 - Pre-Alpha
Classifier: Intended Audience :: Developers
Classifier: Natural Language :: English
Classifier: Programming Language :: Python :: 3
Classifier: Programming Language :: Python :: 3.8
Classifier: Programming Language :: Python :: 3.9
Classifier: Programming Language :: Python :: 3.10
Classifier: Programming Language :: Python :: 3.11
Requires-Dist: appdirs (>=1.4.4,<2.0.0)
Requires-Dist: decopatch (>=1.4.10,<2.0.0)
Requires-Dist: fabric (>=3.0.0,<4.0.0)
Requires-Dist: fsspec (>=2023.1.0,<2024.0.0)
Requires-Dist: gnupg (>=2.3.1,<3.0.0)
Requires-Dist: makefun (>=1.15.0,<2.0.0)
Requires-Dist: pandas
Requires-Dist: pydantic (>=1.10.4,<2.0.0)
Requires-Dist: pymongo
Requires-Dist: pyyaml (>=6.0,<7.0)
Requires-Dist: rich (>=13.3.1,<14.0.0)
Requires-Dist: toml (>=0.10.2,<0.11.0)
